flux_query_builder/__init__.py
flux_query_builder/builder.py
flux_query_builder/__test__/__init__.py
flux_query_builder/__test__/query_builder.py
flux_query_builder/__test__/utility/__init__.py
flux_query_builder/__test__/utility/filter_builder.py
flux_query_builder/__test__/utility/time.py
flux_query_builder/functions/__init__.py
flux_query_builder/functions/aggregateWindow.py
flux_query_builder/functions/base.py
flux_query_builder/functions/bool.py
flux_query_builder/functions/bottom.py
flux_query_builder/functions/buckets.py
flux_query_builder/functions/bytes.py
flux_query_builder/functions/chandeMomentumOscillator.py
flux_query_builder/functions/columns.py
flux_query_builder/functions/contains.py
flux_query_builder/functions/count.py
flux_query_builder/functions/cov.py
flux_query_builder/functions/covariance.py
flux_query_builder/functions/cumulativeSum.py
flux_query_builder/functions/derivative.py
flux_query_builder/functions/die.py
flux_query_builder/functions/difference.py
flux_query_builder/functions/display.py
flux_query_builder/functions/distinct.py
flux_query_builder/functions/doubleEMA.py
flux_query_builder/functions/drop.py
flux_query_builder/functions/duplicate.py
flux_query_builder/functions/duration.py
flux_query_builder/functions/elapsed.py
flux_query_builder/functions/exponentialMovingAverage.py
flux_query_builder/functions/fill.py
flux_query_builder/functions/filter.py
flux_query_builder/functions/findColumn.py
flux_query_builder/functions/findRecord.py
flux_query_builder/functions/first.py
flux_query_builder/functions/float.py
flux_query_builder/functions/from_.py
flux_query_builder/functions/getColumn.py
flux_query_builder/functions/getRecord.py
flux_query_builder/functions/group.py
flux_query_builder/functions/highestAverage.py
flux_query_builder/functions/highestCurrent.py
flux_query_builder/functions/highestMax.py
flux_query_builder/functions/histogram.py
flux_query_builder/functions/histogramQuantile.py
flux_query_builder-1.0.0.dist-info/LICENSE
flux_query_builder-1.0.0.dist-info/METADATA
flux_query_builder-1.0.0.dist-info/WHEEL
flux_query_builder-1.0.0.dist-info/top_level.txt
flux_query_builder-1.0.0.dist-info/RECORD
