Metadata-Version: 2.1
Name: flux-query-builder
Version: 1.0.0
Summary: A python querybuilder for the Flux query language
Author-email: Nico Kraetschmer <kraetschmerni@gmail.com>
License: Apache License
Project-URL: Homepage, https://github.com/Loeffeldude/flux_query_builder
Keywords: flux,influxdb,influx,utility,querybuilder,query,builder,influx-query-builder,flux-query-builder
Classifier: License :: OSI Approved :: Apache Software License
Classifier: Programming Language :: Python
Classifier: Programming Language :: Python :: 3
Requires-Python: >=3.9
License-File: LICENSE
Requires-Dist: dateparser (>=1.1.7)
Provides-Extra: dev
Requires-Dist: freezegun ; extra == 'dev'
